<?xml version='1.0' encoding='utf-8'?>
<document>
  <header>
    <imagefile>Images/Screenshot (1224).png</imagefile>
    <complete>100%</complete>
  </header>
    <segments>
      <segment id='2' start='1189.97214485,200.557103064' end='2370.58495822,1049.5821727' features='kompozycja;wartość-informacyjna;inny-rodzaj-strefy-semantycznej;strefa-podrzędna' state='active'/>
      <segment id='1' start='291.47632312,227.298050139' end='1147.18662953,1250.13927577' features='kompozycja;wartość-informacyjna;inny-rodzaj-strefy-semantycznej;strefa-nadrzędna' state='active'/>
    </segments>
</document>