<?xml version='1.0' encoding='utf-8'?>
<NETWORK VERSION='1.1'>
  <ROOT>
    <FEATURE>
      <NAME>reprezentacje_narracyjne</NAME>
      <STATE>active</STATE>
    </FEATURE>
  </ROOT>
  <SYSTEMS>
    <SYSTEM>
      <NAME>RODZAJ</NAME>
      <EC>reprezentacje_narracyjne</EC>
      <FEATURES>
        <FEATURE>
          <NAME>procesy-narracyjne</NAME>
          <STATE>active</STATE>
        </FEATURE>
        <FEATURE>
          <NAME>obiekty</NAME>
          <STATE>active</STATE>
        </FEATURE>
        <FEATURE>
          <NAME>okoliczności</NAME>
          <STATE>active</STATE>
        </FEATURE>
        <FEATURE>
          <NAME>brak</NAME>
          <STATE>active</STATE>
        </FEATURE>
      </FEATURES>
    </SYSTEM>

    <SYSTEM>
      <NAME>PROCESY-NARRACYJNE</NAME>
      <EC>procesy-narracyjne</EC>
      <FEATURES>
        <FEATURE>
          <NAME>nieagensywne-konwersja</NAME>
          <STATE>active</STATE>
        </FEATURE>
        <FEATURE>
          <NAME>agensywne</NAME>
          <STATE>active</STATE>
        </FEATURE>
      </FEATURES>
    </SYSTEM>

    <SYSTEM>
      <NAME>AGENSYWNE-TYPE</NAME>
      <EC>agensywne</EC>
      <FEATURES>
        <FEATURE>
          <NAME>nieprojekcyjne</NAME>
          <STATE>active</STATE>
        </FEATURE>
        <FEATURE>
          <NAME>projekcyjne</NAME>
          <STATE>active</STATE>
        </FEATURE>
      </FEATURES>
    </SYSTEM>

    <SYSTEM>
      <NAME>NIEPROJEKCYJNE-TYPE</NAME>
      <EC>nieprojekcyjne</EC>
      <FEATURES>
        <FEATURE>
          <NAME>procesy-działania</NAME>
          <STATE>active</STATE>
        </FEATURE>
        <FEATURE>
          <NAME>procesy-reakcji-(nietransakcyjne)</NAME>
          <STATE>active</STATE>
        </FEATURE>
        <FEATURE>
          <NAME>reakcja-(proces-transakcyjny)</NAME>
          <STATE>active</STATE>
        </FEATURE>
      </FEATURES>
    </SYSTEM>

    <SYSTEM>
      <NAME>PROCESY-AKCJI-TYPE</NAME>
      <EC>procesy-działania</EC>
      <FEATURES>
        <FEATURE>
          <NAME>transakcyjne</NAME>
          <STATE>active</STATE>
        </FEATURE>
        <FEATURE>
          <NAME>nietransakcyjne</NAME>
          <STATE>active</STATE>
        </FEATURE>
      </FEATURES>
    </SYSTEM>

    <SYSTEM>
      <NAME>TRANSAKCYJNE-TYPE</NAME>
      <EC>transakcyjne</EC>
      <FEATURES>
        <FEATURE>
          <NAME>jednokierunkowe</NAME>
          <STATE>active</STATE>
        </FEATURE>
        <FEATURE>
          <NAME>wielokierunkowe-(interakcja)</NAME>
          <STATE>active</STATE>
        </FEATURE>
      </FEATURES>
    </SYSTEM>

    <SYSTEM>
      <NAME>NIETRANSAKCYJNE-TYPE</NAME>
      <EC>nietransakcyjne</EC>
      <FEATURES>
        <FEATURE>
          <NAME>aktor-obecny--niewidoczny-cel-akcji</NAME>
          <STATE>active</STATE>
        </FEATURE>
        <FEATURE>
          <NAME>wydarzenie:-cel-widoczny--nie-widać-aktora</NAME>
          <STATE>active</STATE>
        </FEATURE>
      </FEATURES>
    </SYSTEM>

    <SYSTEM>
      <NAME>PROCESY-REAKCJI-(NIETRANSAKCYJNE)-TYPE</NAME>
      <EC>procesy-reakcji-(nietransakcyjne)</EC>
      <FEATURES>
        <FEATURE>
          <NAME>fenomen-widoczny--niewidoczna-reakcja</NAME>
          <STATE>active</STATE>
        </FEATURE>
        <FEATURE>
          <NAME>reakcja-widoczna--niewidoczny-fenomen</NAME>
          <STATE>active</STATE>
        </FEATURE>
      </FEATURES>
    </SYSTEM>

    <SYSTEM>
      <NAME>PROJEKCYJNE-TYPE</NAME>
      <EC>projekcyjne</EC>
      <FEATURES>
        <FEATURE>
          <NAME>procesy-mentalne</NAME>
          <STATE>active</STATE>
        </FEATURE>
        <FEATURE>
          <NAME>procesy-werbalne</NAME>
          <STATE>active</STATE>
        </FEATURE>
      </FEATURES>
    </SYSTEM>

    <SYSTEM>
      <NAME>OBIEKTY</NAME>
      <EC>obiekty</EC>
      <FEATURES>
        <FEATURE>
          <NAME>działania</NAME>
          <STATE>active</STATE>
        </FEATURE>
        <FEATURE>
          <NAME>reakcji</NAME>
          <STATE>active</STATE>
        </FEATURE>
      </FEATURES>
    </SYSTEM>

    <SYSTEM>
      <NAME>AKCJI-TYPE</NAME>
      <EC>działania</EC>
      <FEATURES>
        <FEATURE>
          <NAME>aktor</NAME>
          <STATE>active</STATE>
        </FEATURE>
        <FEATURE>
          <NAME>cel</NAME>
          <STATE>active</STATE>
        </FEATURE>
        <FEATURE>
          <NAME>uczestnicy-interakcji</NAME>
          <STATE>active</STATE>
        </FEATURE>
      </FEATURES>
    </SYSTEM>

    <SYSTEM>
      <NAME>REAKCJI-TYPE</NAME>
      <EC>reakcji</EC>
      <FEATURES>
        <FEATURE>
          <NAME>fenomen</NAME>
          <STATE>active</STATE>
        </FEATURE>
        <FEATURE>
          <NAME>reaktor</NAME>
          <STATE>active</STATE>
        </FEATURE>
      </FEATURES>
    </SYSTEM>

    <SYSTEM>
      <NAME>OKOLICZNOŚCI</NAME>
      <EC>okoliczności</EC>
      <FEATURES>
        <FEATURE>
          <NAME>tło</NAME>
          <STATE>active</STATE>
        </FEATURE>
        <FEATURE>
          <NAME>środki</NAME>
          <STATE>active</STATE>
        </FEATURE>
        <FEATURE>
          <NAME>elementy-towarzyszące</NAME>
          <STATE>active</STATE>
        </FEATURE>
      </FEATURES>
    </SYSTEM>

  </SYSTEMS></NETWORK>